celery_debug/__init__.py
celery_debug/app.py
celery_debug/tasks.py
celery_debug/utils.py
celery_debug-0.1.4.dist-info/LICENSE
celery_debug-0.1.4.dist-info/METADATA
celery_debug-0.1.4.dist-info/WHEEL
celery_debug-0.1.4.dist-info/top_level.txt
celery_debug-0.1.4.dist-info/RECORD
