Metadata-Version: 2.1
Name: celery-debug
Version: 0.1.4
Summary: celery debug tasks.
Home-page: UNKNOWN
Author: Chen YuBo
Maintainer: Chen YuBo
License: MIT
Keywords: celery debug tasks
Platform: UNKNOWN
Classifier: Development Status :: 5 - Production/Stable
Classifier: Intended Audience :: Developers
Classifier: Topic :: Software Development :: Libraries :: Python Modules
Classifier: License :: OSI Approved :: MIT License
Classifier: Programming Language :: Python :: 3
Classifier: Programming Language :: Python :: 3 :: Only
License-File: LICENSE
Requires-Dist: celery
